ai01/__init__.py
ai01/agent/__init__.py
ai01/agent/_exceptions.py
ai01/agent/_models.py
ai01/agent/agent.py
ai01/providers/_api.py
ai01/providers/gemini/__init__.py
ai01/providers/gemini/realtime/__init__.py
ai01/providers/gemini/realtime/_api.py
ai01/providers/gemini/realtime/_exceptions.py
ai01/providers/gemini/realtime/conversation.py
ai01/providers/gemini/realtime/model.py
ai01/providers/openai/__init__.py
ai01/providers/openai/realtime/__init__.py
ai01/providers/openai/realtime/_api.py
ai01/providers/openai/realtime/_exceptions.py
ai01/providers/openai/realtime/conversation.py
ai01/providers/openai/realtime/realtime_model.py
ai01/rtc/__init__.py
ai01/rtc/audio_resampler.py
ai01/rtc/audio_track.py
ai01/rtc/rtc.py
ai01/utils/emitter.py
ai01/utils/socket.py
ai01-0.2.18.dist-info/METADATA
ai01-0.2.18.dist-info/WHEEL
ai01-0.2.18.dist-info/RECORD
