Metadata-Version: 2.1
Name: ai01
Version: 0.2.18
Summary: AI Agent SDK on Huddle01 dRTC Network
Author: Om Gupta
Author-email: omgupta0720@gmail.com
Requires-Python: >=3.12,<4.0
Classifier: Programming Language :: Python :: 3
Classifier: Programming Language :: Python :: 3.12
Requires-Dist: asyncio (>=3.4.3,<4.0.0)
Requires-Dist: av (==11.0.0)
Requires-Dist: google-genai (>=0.5.0,<0.6.0)
Requires-Dist: huddle01 (>=1.1.2,<2.0.0)
Requires-Dist: numpy (>=2.1.3,<3.0.0)
Requires-Dist: pydantic (==2.10.1)
Requires-Dist: pyee (==11.1.0)
Requires-Dist: python-dotenv (>=1.0.1,<2.0.0)
Requires-Dist: sounddevice (>=0.5.1,<0.6.0)
Requires-Dist: uuid (>=1.30,<2.0)
Requires-Dist: websockets (>=13.1,<14.0)
